jupyterlab_h5web/__init__.py
jupyterlab_h5web/_version.py
jupyterlab_h5web/handlers.py
jupyterlab_h5web/utils.py
jupyterlab_h5web/widget.py
jupyterlab_h5web-12.6.1.data/data/etc/jupyter/jupyter_server_config.d/jupyterlab_h5web.json
jupyterlab_h5web-12.6.1.data/data/share/jupyter/labextensions/jupyterlab-h5web/package.json
jupyterlab_h5web-12.6.1.data/data/share/jupyter/labextensions/jupyterlab-h5web/static/179.f9f5c64a42cc1a63ac10.js
jupyterlab_h5web-12.6.1.data/data/share/jupyter/labextensions/jupyterlab-h5web/static/179.f9f5c64a42cc1a63ac10.js.LICENSE.txt
jupyterlab_h5web-12.6.1.data/data/share/jupyter/labextensions/jupyterlab-h5web/static/496.94f5fb09378077dc6e12.js
jupyterlab_h5web-12.6.1.data/data/share/jupyter/labextensions/jupyterlab-h5web/static/530.0c8fff5fae76bd157094.js
jupyterlab_h5web-12.6.1.data/data/share/jupyter/labextensions/jupyterlab-h5web/static/530.0c8fff5fae76bd157094.js.LICENSE.txt
jupyterlab_h5web-12.6.1.data/data/share/jupyter/labextensions/jupyterlab-h5web/static/665.208032baa80f50392f70.js
jupyterlab_h5web-12.6.1.data/data/share/jupyter/labextensions/jupyterlab-h5web/static/761.a7ddb1e7140d9dda9463.js
jupyterlab_h5web-12.6.1.data/data/share/jupyter/labextensions/jupyterlab-h5web/static/761.a7ddb1e7140d9dda9463.js.LICENSE.txt
jupyterlab_h5web-12.6.1.data/data/share/jupyter/labextensions/jupyterlab-h5web/static/821.434339e3e8be4fcdc1a7.js
jupyterlab_h5web-12.6.1.data/data/share/jupyter/labextensions/jupyterlab-h5web/static/953.b79b0e51e535ae40b3bc.js
jupyterlab_h5web-12.6.1.data/data/share/jupyter/labextensions/jupyterlab-h5web/static/remoteEntry.a5900a4f90e4781af4f7.js
jupyterlab_h5web-12.6.1.data/data/share/jupyter/labextensions/jupyterlab-h5web/static/style.js
jupyterlab_h5web-12.6.1.data/data/share/jupyter/labextensions/jupyterlab-h5web/static/third-party-licenses.json
jupyterlab_h5web-12.6.1.data/data/share/jupyter/labextensions/jupyterlab-h5web/install.json
jupyterlab_h5web-12.6.1.dist-info/METADATA
jupyterlab_h5web-12.6.1.dist-info/WHEEL
jupyterlab_h5web-12.6.1.dist-info/licenses/LICENSE.md
jupyterlab_h5web-12.6.1.dist-info/RECORD
