Metadata-Version: 2.4
Name: jupyterlab_h5web
Version: 12.6.1
Summary: A JupyterLab extension to explore and visualize HDF5 file contents.
Project-URL: Homepage, https://github.com/silx-kit/jupyterlab-h5web
Project-URL: Bug Tracker, https://github.com/silx-kit/jupyterlab-h5web/issues
Project-URL: Repository, https://github.com/silx-kit/jupyterlab-h5web.git
Author-email: European Synchrotron Radiation Facility <h5web@esrf.fr>
License: # MIT License
License-File: LICENSE.md
Keywords: h5grove,h5web,hdf5,jupyter,jupyterlab,jupyterlab-extension,nexus
Classifier: Framework :: Jupyter
Classifier: Framework :: Jupyter :: JupyterLab
Classifier: Framework :: Jupyter :: JupyterLab :: 4
Classifier: Framework :: Jupyter :: JupyterLab :: Extensions
Classifier: Framework :: Jupyter :: JupyterLab :: Extensions :: Mime Renderers
Classifier: Framework :: Jupyter :: JupyterLab :: Extensions :: Prebuilt
Classifier: License :: OSI Approved :: MIT License
Classifier: Programming Language :: Python
Classifier: Programming Language :: Python :: 3
Classifier: Programming Language :: Python :: 3.9
Classifier: Programming Language :: Python :: 3.10
Classifier: Programming Language :: Python :: 3.11
Classifier: Programming Language :: Python :: 3.12
Classifier: Programming Language :: Python :: 3.13
Requires-Python: >=3.9
Requires-Dist: h5grove==2.3.0
Requires-Dist: h5py>=3.5
Requires-Dist: jupyter-server<3,>=2.4.0
Provides-Extra: full
Requires-Dist: hdf5plugin; extra == 'full'
